{
  "version": 1,
  "width": 130,
  "height": 33,
  "duration": 68.735703,
  "command": null,
  "title": "Samba setup with Ansible",
  "env": {
    "TERM": "xterm-256color",
    "SHELL": "/bin/bash"
  },
  "stdout": [
    [
      0.121086,
      "\u001b]0;hostmorke@voidstation: ~/dev/ansiblefiles/playbooks/samba-server\u0007~/dev/ansiblefiles/playbooks/samba-server~> "
    ],
    [
      2.0,
      "l"
    ],
    [
      0.151597,
      "s"
    ],
    [
      0.264192,
      " "
    ],
    [
      0.207849,
      "-"
    ],
    [
      0.144043,
      "l"
    ],
    [
      0.504679,
      "\r\n"
    ],
    [
      0.016426,
      "total 16\r\n"
    ],
    [
      0.000685,
      "-rw-r--r-- 1 hostmorke hostmorke  116 Feb  1 11:46 ansible.cfg\r\n"
    ],
    [
      0.000812,
      "drwxr-xr-x 2 hostmorke hostmorke 4096 Feb  1 10:42 \u001b[0m\u001b[01;34mfiles\u001b[0m\r\n"
    ],
    [
      0.001545,
      "-rw-r--r-- 1 hostmorke hostmorke   18 Feb  1 10:41 hosts\r\n"
    ],
    [
      0.000392,
      "-rw-r--r-- 1 hostmorke hostmorke  970 Feb  1 12:13 setup.yml\r\n"
    ],
    [
      0.007915,
      "\u001b]0;hostmorke@voidstation: ~/dev/ansiblefiles/playbooks/samba-server\u0007~/dev/ansiblefiles/playbooks/samba-server~> "
    ],
    [
      1.827605,
      "v"
    ],
    [
      0.744051,
      "i"
    ],
    [
      0.103792,
      "m"
    ],
    [
      0.375951,
      " "
    ],
    [
      0.448602,
      "a"
    ],
    [
      0.300033,
      "nsible.cfg "
    ],
    [
      0.398197,
      "\r\n"
    ],
    [
      0.078155,
      "\u001b[?2004h"
    ],
    [
      0.002866,
      "\u001b[?1049h\u001b[?1h\u001b=\u001b[?2004h"
    ],
    [
      0.001402,
      "\u001b[1;33r\u001b[?12h\u001b[?12l\u001b[27m\u001b[23m\u001b[29m\u001b[m\u001b[38;5;231m\u001b[48;5;235m\u001b[H\u001b[2J\u001b[?25l\u001b[33;1H\"ansible.cfg\""
    ],
    [
      0.000497,
      " 6L, 116C"
    ],
    [
      0.153357,
      "\u001b[2;1H▽\u001b[6n"
    ],
    [
      0.00309,
      "\u001b[2;1H  \u001b[1;1H"
    ],
    [
      0.000271,
      "\u001b[>c"
    ],
    [
      0.000291,
      "\u001b]10;?\u0007\u001b]11;?\u0007"
    ],
    [
      0.042716,
      "\u001b[1;1H\u001b[38;5;232m\u001b[48;5;154m ansible.cfg \u001b[m\u001b[38;5;231m\u001b[48;5;235m\u001b[38;5;154m\u001b[48;5;235m\u001b[m\u001b[38;5;231m\u001b[48;5;235m\u001b[1;15H\u001b[38;5;121m\u001b[48;5;235m                                                                                                         \u001b[m\u001b[38;5;231m\u001b[48;5;235m\u001b[38;5;235m\u001b[48;5;235m\u001b[m\u001b[38;5;231m\u001b[48;5;235m\u001b[1;121H\u001b[38;5;214m\u001b[48;5;235m\u001b[m\u001b[38;5;231m\u001b[48;5;235m\u001b[1;122H\u001b[38;5;232m\u001b[48;5;214m buffers \u001b[m\u001b[38;5;231m\u001b[48;5;235m\u001b[2;1H\u001b[38;5;102m\u001b[48;5;237m  1 \u001b[m\u001b[38;5;231m\u001b[48;5;235m\u001b[4m\u001b[38;5;197m[\u001b[m\u001b[38;5;231m\u001b[48;5;235m\u001b[38;5;197mdefaults\u001b[m\u001b[38;5;231m\u001b[48;5;235m\u001b[4m\u001b[38;5;197m]\u001b[m\u001b[38;5;231m\u001b[48;5;235m\r\n\u001b[38;5;102m\u001b[48;5;237m  2 \u001b[m\u001b[38;5;231m\u001b[48;5;235minventory = hosts\r\n\u001b[38;5;102m\u001b[48;5;237m  3 \u001b[m\u001b[38;5;231m\u001b[48;5;235mhost_key_checking = \u001b[38;5;186mFalse\u001b[m\u001b[38;5;231m\u001b[48;5;235m\r\n\u001b[38;5;102m\u001b[48;5;237m  4 \u001b[m\u001b[38;5;231m\u001b[48;5;235mremote_user = adminuser\r\n\u001b[38;5;102m\u001b[48;5;237m  5 \u001b[m\u001b[38;5;231m\u001b[48;5;235mbecome = \u001b[38;5;186mTrue\u001b[m\u001b[38;5;231m\u001b[48;5;235m\r\n\u001b[38;5;102m\u001b[48;5;237m  6 \u001b[m\u001b"
    ],
    [
      8.2e-05,
      "[38;5;231m\u001b[48;5;235mbecome_ask_pass = \u001b[38;5;186mTrue\u001b[m\u001b[38;5;231m\u001b[48;5;235m\r\n\u001b[38;5;59m\u001b[48;5;236m~                                                                                                                                 \u001b[9;1H~                                                                                                                                 \u001b[10;1H~                                                                                                                                 \u001b[11;1H~                                                                                                                                 \u001b[12;1H~                                                                                                                                 \u001b[13;1H~                                                                                                                                 \u001b[14;1H~                                                                                                   "
    ],
    [
      0.004479,
      "                              \u001b[15;1H~                                                                                                                                 \u001b[16;1H~                                                                                                                                 \u001b[17;1H~                                                                                                                                 \u001b[18;1H~                                                                                                                                 \u001b[19;1H~                                                                                                                                 \u001b[20;1H~                                                                                                                                 \u001b[21;1H~                                                                                                                                 \u001b[22;1H~                           "
    ],
    [
      8.9e-05,
      "                                                                                                      \u001b[23;1H~                                                                                                                                 \u001b[24;1H~                                                                                                                                 \u001b[25;1H~                                                                                                                                 \u001b[26;1H~                                                                                                                                 \u001b[27;1H~                                                                                                                                 \u001b[28;1H~                                                                                                                                 \u001b[29;1H~                                                                                           "
    ],
    [
      0.004468,
      "                                      \u001b[30;1H~                                                                                                                                 \u001b[31;1H~                                                                                                                                 \u001b[m\u001b[38;5;231m\u001b[48;5;235m\u001b[32;1H\u001b[38;5;232m\u001b[48;5;154m \u001b[m\u001b[38;5;231m\u001b[48;5;235m\u001b[1m\u001b[38;5;232m\u001b[48;5;154mNORMAL\u001b[m\u001b[38;5;231m\u001b[48;5;235m\u001b[38;5;232m\u001b[48;5;154m \u001b[m\u001b[38;5;231m\u001b[48;5;235m\u001b[38;5;154m\u001b[48;5;238m\u001b[m\u001b[38;5;231m\u001b[48;5;235m\u001b[32;10H\u001b[38;5;238m\u001b[48;5;235m\u001b[m\u001b[38;5;231m\u001b[48;5;235m\u001b[32;11H\u001b[38;5;121m\u001b[48;5;235m ansible.cfg                                                                     \u001b[m\u001b[38;5;231m\u001b[48;5;235m\u001b[38;5;235m\u001b[48;5;235m\u001b[m\u001b[38;5;231m\u001b[48;5;235m\u001b[32;93H\u001b[38;5;121m\u001b[48;5;235m cfg \u001b[m\u001b[38;5;231m\u001b[48;5;235m\u001b[38;5;238m\u001b[48;5;235m\u001b[m\u001b[38;5;231m\u001b[48;5;235m\u001b[32;99H\u001b[38;5;222m\u001b[48;5;238m utf-8[unix] \u001b[m\u001b[38;5;231m\u001b[48;5;235m\u001b[38;5;154m\u001b[48;5;238m\u001b[m\u001b[38;5;231m\u001b[48;5;235m\u001b[32;"
    ],
    [
      0.000101,
      "113H\u001b[38;5;232m\u001b[48;5;154m  16% \u001b[m\u001b[38;5;231m\u001b[48;5;235m\u001b[32;120H\u001b[1m\u001b[38;5;232m\u001b[48;5;154m   1\u001b[m\u001b[38;5;231m\u001b[48;5;235m\u001b[38;5;232m\u001b[48;5;154m:  1  \u001b[m\u001b[38;5;231m\u001b[48;5;235m\u001b[38;5;166m\u001b[48;5;154m\u001b[2;5H\u001b[?25h"
    ],
    [
      2.0,
      "\u001b[?25l\u001b[m\u001b[38;5;231m\u001b[48;5;235m\u001b[33;1H\u001b[K\u001b[33;1H:\u001b[?2004h\u001b[?25h"
    ],
    [
      0.480146,
      "q\u001b[?25l\u001b[?25h"
    ],
    [
      0.329467,
      "\r"
    ],
    [
      0.025462,
      "\u001b[?25l"
    ],
    [
      0.004003,
      "\u001b[?2004l"
    ],
    [
      0.103609,
      "\u001b[33;1H\u001b[K\u001b[33;1H\u001b[?2004l\u001b[?1l\u001b>\u001b[?25h\u001b[?1049l"
    ],
    [
      0.010528,
      "\u001b]0;hostmorke@voidstation: ~/dev/ansiblefiles/playbooks/samba-server\u0007~/dev/ansiblefiles/playbooks/samba-server~> "
    ],
    [
      1.495224,
      "v"
    ],
    [
      0.143505,
      "i"
    ],
    [
      0.112081,
      "m"
    ],
    [
      0.191847,
      " "
    ],
    [
      0.728464,
      "h"
    ],
    [
      0.279935,
      "o"
    ],
    [
      0.165676,
      "sts "
    ],
    [
      0.507115,
      "\r\n"
    ],
    [
      0.074757,
      "\u001b[?2004h"
    ],
    [
      0.00323,
      "\u001b[?1049h\u001b[?1h\u001b=\u001b[?2004h"
    ],
    [
      0.00127,
      "\u001b[1;33r\u001b[?12h\u001b[?12l\u001b[27m\u001b[23m\u001b[29m\u001b[m\u001b[38;5;231m\u001b[48;5;235m\u001b[H\u001b[2J\u001b[?25l\u001b[33;1H\"hosts\""
    ],
    [
      0.00037,
      " 2L, 18C"
    ],
    [
      0.110023,
      "\u001b[2;1H▽\u001b[6n"
    ],
    [
      0.003123,
      "\u001b[2;1H  \u001b[1;1H"
    ],
    [
      0.000262,
      "\u001b[>c"
    ],
    [
      0.000328,
      "\u001b]10;?\u0007\u001b]11;?\u0007"
    ],
    [
      0.041923,
      "\u001b[1;1H\u001b[38;5;232m\u001b[48;5;154m hosts \u001b[m\u001b[38;5;231m\u001b[48;5;235m\u001b[38;5;154m\u001b[48;5;235m\u001b[m\u001b[38;5;231m\u001b[48;5;235m\u001b[1;9H\u001b[38;5;121m\u001b[48;5;235m                                                                                                               \u001b[m\u001b[38;5;231m\u001b[48;5;235m\u001b[38;5;235m\u001b[48;5;235m\u001b[m\u001b[38;5;231m\u001b[48;5;235m\u001b[1;121H\u001b[38;5;214m\u001b[48;5;235m\u001b[m\u001b[38;5;231m\u001b[48;5;235m\u001b[1;122H\u001b[38;5;232m\u001b[48;5;214m buffers \u001b[m\u001b[38;5;231m\u001b[48;5;235m\u001b[2;1H\u001b[38;5;102m\u001b[48;5;237m  1 \u001b[m\u001b[38;5;231m\u001b[48;5;235m\u001b[4m\u001b[38;5;197m[\u001b[m\u001b[38;5;231m\u001b[48;5;235mnas\u001b[4m\u001b[38;5;197m]\u001b[m\u001b[38;5;231m\u001b[48;5;235m\r\n\u001b[38;5;102m\u001b[48;5;237m  2 \u001b[m\u001b[38;5;231m\u001b[48;5;235m10.69.0.199\r\n\u001b[38;5;59m\u001b[48;5;236m~                                                                                                                                 \u001b[5;1H~                                                                                                                                 \u001b[6;1H~                                                                            "
    ],
    [
      8.6e-05,
      "                                                     \u001b[7;1H~                                                                                                                                 \u001b[8;1H~                                                                                                                                 \u001b[9;1H~                                                                                                                                 \u001b[10;1H~                                                                                                                                 \u001b[11;1H~                                                                                                                                 \u001b[12;1H~                                                                                                                                 \u001b[13;1H~                                                                                                                                 "
    ],
    [
      0.00413,
      "\u001b[14;1H~                                                                                                                                 \u001b[15;1H~                                                                                                                                 \u001b[16;1H~                                                                                                                                 \u001b[17;1H~                                                                                                                                 \u001b[18;1H~                                                                                                                                 \u001b[19;1H~                                                                                                                                 \u001b[20;1H~                                                                                                                                 \u001b[21;1H~                                                         "
    ],
    [
      0.000103,
      "                                                                        \u001b[22;1H~                                                                                                                                 \u001b[23;1H~                                                                                                                                 \u001b[24;1H~                                                                                                                                 \u001b[25;1H~                                                                                                                                 \u001b[26;1H~                                                                                                                                 \u001b[27;1H~                                                                                                                                 \u001b[28;1H~                                                                                                                         "
    ],
    [
      0.003776,
      "        \u001b[29;1H~                                                                                                                                 \u001b[30;1H~                                                                                                                                 \u001b[31;1H~                                                                                                                                 \u001b[m\u001b[38;5;231m\u001b[48;5;235m\u001b[32;1H\u001b[38;5;232m\u001b[48;5;154m \u001b[m\u001b[38;5;231m\u001b[48;5;235m\u001b[1m\u001b[38;5;232m\u001b[48;5;154mNORMAL\u001b[m\u001b[38;5;231m\u001b[48;5;235m\u001b[38;5;232m\u001b[48;5;154m \u001b[m\u001b[38;5;231m\u001b[48;5;235m\u001b[38;5;154m\u001b[48;5;238m\u001b[m\u001b[38;5;231m\u001b[48;5;235m\u001b[32;10H\u001b[38;5;238m\u001b[48;5;235m\u001b[m\u001b[38;5;231m\u001b[48;5;235m\u001b[32;11H\u001b[38;5;121m\u001b[48;5;235m hosts                                                                                \u001b[m\u001b[38;5;231m\u001b[48;5;235m\u001b[38;5;235m\u001b[48;5;235m\u001b[m\u001b[38;5;231m\u001b[48;5;235m\u001b[32;98H\u001b[38;5;238m\u001b[48;5;235m\u001b[m\u001b[38;5;231m\u001b[48;5;235m\u001b[32;99H\u001b[38;5;222m\u001b[48;5;238m utf-8[unix] \u001b[m\u001b[38;5;231m\u001b[48;5"
    ],
    [
      0.000107,
      ";235m\u001b[38;5;154m\u001b[48;5;238m\u001b[m\u001b[38;5;231m\u001b[48;5;235m\u001b[32;113H\u001b[38;5;232m\u001b[48;5;154m  50% \u001b[m\u001b[38;5;231m\u001b[48;5;235m\u001b[32;120H\u001b[1m\u001b[38;5;232m\u001b[48;5;154m   1\u001b[m\u001b[38;5;231m\u001b[48;5;235m\u001b[38;5;232m\u001b[48;5;154m:  1  \u001b[m\u001b[38;5;231m\u001b[48;5;235m\u001b[38;5;166m\u001b[48;5;154m\u001b[2;5H\u001b[?25h"
    ],
    [
      1.235305,
      "\u001b[?25l\u001b[m\u001b[38;5;231m\u001b[48;5;235m\u001b[33;1H\u001b[K\u001b[33;1H:\u001b[?2004h\u001b[?25h"
    ],
    [
      0.360254,
      "q\u001b[?25l\u001b[?25h"
    ],
    [
      0.345889,
      "\r"
    ],
    [
      0.026642,
      "\u001b[?25l"
    ],
    [
      0.003795,
      "\u001b[?2004l"
    ],
    [
      0.105764,
      "\u001b[33;1H\u001b[K\u001b[33;1H\u001b[?2004l\u001b[?1l\u001b>\u001b[?25h\u001b[?1049l"
    ],
    [
      0.006354,
      "\u001b]0;hostmorke@voidstation: ~/dev/ansiblefiles/playbooks/samba-server\u0007~/dev/ansiblefiles/playbooks/samba-server~> "
    ],
    [
      0.799397,
      "v"
    ],
    [
      0.231757,
      "i"
    ],
    [
      0.09644,
      "m"
    ],
    [
      0.231654,
      " "
    ],
    [
      0.70453,
      "f"
    ],
    [
      0.311535,
      "i"
    ],
    [
      0.137962,
      "les/"
    ],
    [
      0.898927,
      "smb.conf "
    ],
    [
      0.282242,
      "\r\n"
    ],
    [
      0.076304,
      "\u001b[?2004h"
    ],
    [
      0.002806,
      "\u001b[?1049h\u001b[?1h\u001b=\u001b[?2004h"
    ],
    [
      0.001397,
      "\u001b[1;33r\u001b[?12h\u001b[?12l\u001b[27m\u001b[23m\u001b[29m\u001b[m\u001b[38;5;231m\u001b[48;5;235m\u001b[H\u001b[2J\u001b[?25l\u001b[33;1H\"files/smb.conf\""
    ],
    [
      0.000543,
      " 35L, 828C"
    ],
    [
      0.211855,
      "\u001b[2;1H▽\u001b[6n"
    ],
    [
      0.003162,
      "\u001b[2;1H  \u001b[1;1H"
    ],
    [
      0.00028,
      "\u001b[>c"
    ],
    [
      0.000198,
      "\u001b]10;?\u0007\u001b]11;?\u0007"
    ],
    [
      0.042673,
      "\u001b[1;1H\u001b[38;5;232m\u001b[48;5;154m smb.conf \u001b[m\u001b[38;5;231m\u001b[48;5;235m\u001b[38;5;154m\u001b[48;5;235m\u001b[m\u001b[38;5;231m\u001b[48;5;235m\u001b[1;12H\u001b[38;5;121m\u001b[48;5;235m                                                                                                            \u001b[m\u001b[38;5;231m\u001b[48;5;235m\u001b[38;5;235m\u001b[48;5;235m\u001b[m\u001b[38;5;231m\u001b[48;5;235m\u001b[1;121H\u001b[38;5;214m\u001b[48;5;235m\u001b[m\u001b[38;5;231m\u001b[48;5;235m\u001b[1;122H\u001b[38;5;232m\u001b[48;5;214m buffers \u001b[m\u001b[38;5;231m\u001b[48;5;235m\u001b[2;1H\u001b[38;5;102m\u001b[48;5;237m  1 \u001b[m\u001b[38;5;231m\u001b[48;5;235m\u001b[4m\u001b[38;5;197m[\u001b[m\u001b[38;5;231m\u001b[48;5;235m\u001b[38;5;197mglobal\u001b[m\u001b[38;5;231m\u001b[48;5;235m\u001b[4m\u001b[38;5;197m]\u001b[m\u001b[38;5;231m\u001b[48;5;235m\r\n\u001b[38;5;102m\u001b[48;5;237m  2 \u001b[m\u001b[38;5;231m\u001b[48;5;235m    \u001b[38;5;197mworkgroup\u001b[m\u001b[38;5;231m\u001b[48;5;235m = PDBE\r\n\u001b[38;5;102m\u001b[48;5;237m  3 \u001b[m\u001b[38;5;231m\u001b[48;5;235m    \u001b[38;5;197mserver\u001b[m\u001b[38;5;231m\u001b[48;5;235m \u001b[38;5;197mstring\u001b[m\u001b[38;5;231m\u001b[48;5;235m = \u001b[38;5;197m%h\u001b[m\u001b[38;5;231m\u001b[48;5;235m\r\n\u001b[38;5;102m\u001b[48;5;237m  4 \u001b[m\u001b[38;5;231m\u001b[48;5;235m    \u001b[38;5;197mmap\u001b[m\u001b[38;5;231m\u001b[48;5;235m \u001b[38;5;"
    ],
    [
      8.4e-05,
      "197mto\u001b[m\u001b[38;5;231m\u001b[48;5;235m \u001b[38;5;197mguest\u001b[m\u001b[38;5;231m\u001b[48;5;235m = Bad User\r\n\u001b[38;5;102m\u001b[48;5;237m  5 \u001b[m\u001b[38;5;231m\u001b[48;5;235m    \u001b[38;5;197mobey\u001b[m\u001b[38;5;231m\u001b[48;5;235m \u001b[38;5;197mpam\u001b[m\u001b[38;5;231m\u001b[48;5;235m \u001b[38;5;197mrestrictions\u001b[m\u001b[38;5;231m\u001b[48;5;235m = Yes\r\n\u001b[38;5;102m\u001b[48;5;237m  6 \u001b[m\u001b[38;5;231m\u001b[48;5;235m    \u001b[38;5;197mpam\u001b[m\u001b[38;5;231m\u001b[48;5;235m \u001b[38;5;197mpassword\u001b[m\u001b[38;5;231m\u001b[48;5;235m \u001b[38;5;197mchange\u001b[m\u001b[38;5;231m\u001b[48;5;235m = Yes\r\n\u001b[38;5;102m\u001b[48;5;237m  7 \u001b[m\u001b[38;5;231m\u001b[48;5;235m    \u001b[38;5;197mpasswd\u001b[m\u001b[38;5;231m\u001b[48;5;235m \u001b[38;5;197mprogram\u001b[m\u001b[38;5;231m\u001b[48;5;235m = /usr/bin/passwd \u001b[38;5;197m%u\u001b[m\u001b[38;5;231m\u001b[48;5;235m\r\n\u001b[38;5;102m\u001b[48;5;237m  8 \u001b[m\u001b[38;5;231m\u001b[48;5;235m    \u001b[38;5;197mpasswd\u001b[m\u001b[38;5;231m\u001b[48;5;235m \u001b[38;5;197mchat\u001b[m\u001b[38;5;231m\u001b[48;5;235m = *Enter\\snew\\s*\\spassword:* \u001b[38;5;197m%n\u001b[m\u001b[38;5;231m\u001b[48;5;235m\\n *Retype\\snew\\s*\\spassword:* \u001b[38;5;197m%n\u001b[m\u001b[38;5;231m\u001b[48;5;235m\\n *password\\supdated\\ssuccessfully* .\r\n\u001b[38;5;102m\u001b[48;5;237m  9 "
    ],
    [
      0.006348,
      "\u001b[m\u001b[38;5;231m\u001b[48;5;235m    \u001b[38;5;197munix\u001b[m\u001b[38;5;231m\u001b[48;5;235m \u001b[38;5;197mpassword\u001b[m\u001b[38;5;231m\u001b[48;5;235m \u001b[38;5;197msync\u001b[m\u001b[38;5;231m\u001b[48;5;235m = Yes\r\n\u001b[38;5;102m\u001b[48;5;237m 10 \u001b[m\u001b[38;5;231m\u001b[48;5;235m    \u001b[38;5;197msyslog\u001b[m\u001b[38;5;231m\u001b[48;5;235m = 0\r\n\u001b[38;5;102m\u001b[48;5;237m 11 \u001b[m\u001b[38;5;231m\u001b[48;5;235m    \u001b[38;5;197mlog\u001b[m\u001b[38;5;231m\u001b[48;5;235m \u001b[38;5;197mfile\u001b[m\u001b[38;5;231m\u001b[48;5;235m = /var/log/samba/log.\u001b[38;5;197m%m\u001b[m\u001b[38;5;231m\u001b[48;5;235m\r\n\u001b[38;5;102m\u001b[48;5;237m 12 \u001b[m\u001b[38;5;231m\u001b[48;5;235m    \u001b[38;5;197mmax\u001b[m\u001b[38;5;231m\u001b[48;5;235m \u001b[38;5;197mlog\u001b[m\u001b[38;5;231m\u001b[48;5;235m \u001b[38;5;197msize\u001b[m\u001b[38;5;231m\u001b[48;5;235m = 1000\r\n\u001b[38;5;102m\u001b[48;5;237m 13 \u001b[m\u001b[38;5;231m\u001b[48;5;235m    \u001b[38;5;197mdns\u001b[m\u001b[38;5;231m\u001b[48;5;235m \u001b[38;5;197mproxy\u001b[m\u001b[38;5;231m\u001b[48;5;235m = No\r\n\u001b[38;5;102m\u001b[48;5;237m 14 \u001b[m\u001b[38;5;231m\u001b[48;5;235m    usershare \u001b[38;5;197mallow\u001b[m\u001b[38;5;231m\u001b[48;5;235m guests = No\r\n\u001b[38;5;102m\u001b[48;5;237m 15 \u001b[m\u001b[38;5;231m\u001b[48;5;235m    \u001b[38;5;197mpanic\u001b[m\u001b[38;5;231m\u001b[48;5;235m \u001b[38;5;197maction"
    ],
    [
      0.000172,
      "\u001b[m\u001b[38;5;231m\u001b[48;5;235m = /usr/share/samba/panic-action \u001b[38;5;197m%d\u001b[m\u001b[38;5;231m\u001b[48;5;235m\r\n\u001b[38;5;102m\u001b[48;5;237m 16 \u001b[m\u001b[38;5;231m\u001b[48;5;235m    idmap config * : backend = tdb\r\n\u001b[38;5;102m\u001b[48;5;237m 17 \r\n 18 \u001b[m\u001b[38;5;231m\u001b[48;5;235m\u001b[38;5;197m[rmc]\u001b[m\u001b[38;5;231m\u001b[48;5;235m\r\n\u001b[38;5;102m\u001b[48;5;237m 19 \u001b[m\u001b[38;5;231m\u001b[48;5;235m    \u001b[38;5;197mpath\u001b[m\u001b[38;5;231m\u001b[48;5;235m = /mnt/storage/rmc\r\n\u001b[38;5;102m\u001b[48;5;237m 20 \u001b[m\u001b[38;5;231m\u001b[48;5;235m    \u001b[38;5;197musername\u001b[m\u001b[38;5;231m\u001b[48;5;235m = rmc\r\n\u001b[38;5;102m\u001b[48;5;237m 21 \u001b[m\u001b[38;5;231m\u001b[48;5;235m    \u001b[38;5;197mvalid\u001b[m\u001b[38;5;231m\u001b[48;5;235m \u001b[38;5;197musers\u001b[m\u001b[38;5;231m\u001b[48;5;235m = rmc\r\n\u001b[38;5;102m\u001b[48;5;237m 22 \u001b[m\u001b[38;5;231m\u001b[48;5;235m    \u001b[38;5;197mread\u001b[m\u001b[38;5;231m\u001b[48;5;235m \u001b[38;5;197monly\u001b[m\u001b[38;5;231m\u001b[48;5;235m = No\r\n\u001b[38;5;102m\u001b[48;5;237m 23 \u001b[m\u001b[38;5;231m\u001b[48;5;235m    \u001b[38;5;197minherit\u001b[m\u001b[38;5;231m\u001b[48;5;235m \u001b[38;5;197mpermissions\u001b[m\u001b[38;5;231m\u001b[48;5;235m = Yes\r\n\u001b[38;5;102m\u001b[48;5;237m 24 \u001b[m\u001b[38;5;231m\u001b[48;5;235m    "
    ],
    [
      0.006554,
      "\u001b[38;5;197minherit\u001b[m\u001b[38;5;231m\u001b[48;5;235m \u001b[38;5;197macls\u001b[m\u001b[38;5;231m\u001b[48;5;235m = Yes\r\n\u001b[38;5;102m\u001b[48;5;237m 25 \u001b[m\u001b[38;5;231m\u001b[48;5;235m    \u001b[38;5;197minherit\u001b[m\u001b[38;5;231m\u001b[48;5;235m owner = Yes\r\n\u001b[38;5;102m\u001b[48;5;237m 26 \u001b[m\u001b[38;5;231m\u001b[48;5;235m    \u001b[38;5;197monly\u001b[m\u001b[38;5;231m\u001b[48;5;235m \u001b[38;5;197muser\u001b[m\u001b[38;5;231m\u001b[48;5;235m = Yes\r\n\u001b[38;5;102m\u001b[48;5;237m 27 \r\n 28 \u001b[m\u001b[38;5;231m\u001b[48;5;235m\u001b[38;5;197m[pdbe]\u001b[m\u001b[38;5;231m\u001b[48;5;235m\r\n\u001b[38;5;102m\u001b[48;5;237m 29 \u001b[m\u001b[38;5;231m\u001b[48;5;235m    \u001b[38;5;197mpath\u001b[m\u001b[38;5;231m\u001b[48;5;235m = /mnt/storage/pdbe\r\n\u001b[38;5;102m\u001b[48;5;237m 30 \u001b[m\u001b[38;5;231m\u001b[48;5;235m    \u001b[38;5;197musername\u001b[m\u001b[38;5;231m\u001b[48;5;235m = pdbe\r\n\u001b[38;5;232m\u001b[48;5;154m \u001b[m\u001b[38;5;231m\u001b[48;5;235m\u001b[1m\u001b[38;5;232m\u001b[48;5;154mNORMAL\u001b[m\u001b[38;5;231m\u001b[48;5;235m\u001b[38;5;232m\u001b[48;5;154m \u001b[m\u001b[38;5;231m\u001b[48;5;235m\u001b[38;5;154m\u001b[48;5;238m\u001b[m\u001b[38;5;231m\u001b[48;5;235m\u001b[32;10H\u001b[38;5;238m\u001b[48;5;235m\u001b[m\u001b[38;5;231m\u001b[48;5;235m\u001b[32;11H\u001b[38;5;121m\u001b[48;5;235m files/smb.conf                                            "
    ],
    [
      8.7e-05,
      "                    \u001b[m\u001b[38;5;231m\u001b[48;5;235m\u001b[38;5;235m\u001b[48;5;235m\u001b[m\u001b[38;5;231m\u001b[48;5;235m\u001b[32;91H\u001b[38;5;121m\u001b[48;5;235m samba \u001b[m\u001b[38;5;231m\u001b[48;5;235m\u001b[38;5;238m\u001b[48;5;235m\u001b[m\u001b[38;5;231m\u001b[48;5;235m\u001b[32;99H\u001b[38;5;222m\u001b[48;5;238m utf-8[unix] \u001b[m\u001b[38;5;231m\u001b[48;5;235m\u001b[38;5;154m\u001b[48;5;238m\u001b[m\u001b[38;5;231m\u001b[48;5;235m\u001b[32;113H\u001b[38;5;232m\u001b[48;5;154m   2% \u001b[m\u001b[38;5;231m\u001b[48;5;235m\u001b[32;120H\u001b[1m\u001b[38;5;232m\u001b[48;5;154m   1\u001b[m\u001b[38;5;231m\u001b[48;5;235m\u001b[38;5;232m\u001b[48;5;154m:  1  \u001b[m\u001b[38;5;231m\u001b[48;5;235m\u001b[38;5;166m\u001b[48;5;154m\u001b[2;5H\u001b[?25h"
    ],
    [
      0.933463,
      "\u001b[?25l\u001b[m\u001b[38;5;231m\u001b[48;5;235m\u001b[38;5;197m[global]\u001b[m\u001b[38;5;231m\u001b[48;5;235m\u001b[32;116H\u001b[38;5;232m\u001b[48;5;154m5\u001b[m\u001b[38;5;231m\u001b[48;5;235m\u001b[6C\u001b[1m\u001b[38;5;232m\u001b[48;5;154m2\u001b[m\u001b[38;5;231m\u001b[48;5;235m\u001b[38;5;232m\u001b[48;5;154m:  4\u001b[3;8H\u001b[?25h"
    ],
    [
      0.667708,
      "\u001b[32;116H8\u001b[m\u001b[38;5;231m\u001b[48;5;235m\u001b[6C\u001b[1m\u001b[38;5;232m\u001b[48;5;154m3\u001b[m\u001b[38;5;231m\u001b[48;5;235m\u001b[38;5;232m\u001b[48;5;154m:\u001b[4;8H"
    ],
    [
      0.043905,
      "\u001b[32;115H11\u001b[m\u001b[38;5;231m\u001b[48;5;235m\u001b[6C\u001b[1m\u001b[38;5;232m\u001b[48;5;154m4\u001b[m\u001b[38;5;231m\u001b[48;5;235m\u001b[38;5;232m\u001b[48;5;154m:\u001b[5;8H"
    ],
    [
      0.043976,
      "\u001b[32;116H4\u001b[m\u001b[38;5;231m\u001b[48;5;235m\u001b[6C\u001b[1m\u001b[38;5;232m\u001b[48;5;154m5\u001b[m\u001b[38;5;231m\u001b[48;5;235m\u001b[38;5;232m\u001b[48;5;154m:\u001b[6;8H"
    ],
    [
      0.043588,
      "\u001b[32;116H7\u001b[m\u001b[38;5;231m\u001b[48;5;235m\u001b[6C\u001b[1m\u001b[38;5;232m\u001b[48;5;154m6\u001b[m\u001b[38;5;231m\u001b[48;5;235m\u001b[38;5;232m\u001b[48;5;154m:\u001b[7;8H"
    ],
    [
      0.047808,
      "\u001b[32;115H20\u001b[m\u001b[38;5;231m\u001b[48;5;235m\u001b[6C\u001b[1m\u001b[38;5;232m\u001b[48;5;154m7\u001b[m\u001b[38;5;231m\u001b[48;5;235m\u001b[38;5;232m\u001b[48;5;154m:\u001b[8;8H"
    ],
    [
      0.044712,
      "\u001b[32;116H2\u001b[m\u001b[38;5;231m\u001b[48;5;235m\u001b[6C\u001b[1m\u001b[38;5;232m\u001b[48;5;154m8\u001b[m\u001b[38;5;231m\u001b[48;5;235m\u001b[38;5;232m\u001b[48;5;154m:\u001b[9;8H"
    ],
    [
      0.046296,
      "\u001b[32;116H5\u001b[m\u001b[38;5;231m\u001b[48;5;235m\u001b[6C\u001b[1m\u001b[38;5;232m\u001b[48;5;154m9\u001b[m\u001b[38;5;231m\u001b[48;5;235m\u001b[38;5;232m\u001b[48;5;154m:\u001b[10;8H"
    ],
    [
      0.04161,
      "\u001b[32;116H8\u001b[m\u001b[38;5;231m\u001b[48;5;235m\u001b[5C\u001b[1m\u001b[38;5;232m\u001b[48;5;154m10\u001b[m\u001b[38;5;231m\u001b[48;5;235m\u001b[38;5;232m\u001b[48;5;154m:\u001b[11;8H"
    ],
    [
      0.045998,
      "\u001b[32;115H31\u001b[m\u001b[38;5;231m\u001b[48;5;235m\u001b[6C\u001b[1m\u001b[38;5;232m\u001b[48;5;154m1\u001b[m\u001b[38;5;231m\u001b[48;5;235m\u001b[38;5;232m\u001b[48;5;154m:\u001b[12;8H"
    ],
    [
      0.042604,
      "\u001b[32;116H4\u001b[m\u001b[38;5;231m\u001b[48;5;235m\u001b[6C\u001b[1m\u001b[38;5;232m\u001b[48;5;154m2\u001b[m\u001b[38;5;231m\u001b[48;5;235m\u001b[38;5;232m\u001b[48;5;154m:\u001b[13;8H"
    ],
    [
      0.043833,
      "\u001b[32;116H7\u001b[m\u001b[38;5;231m\u001b[48;5;235m\u001b[6C\u001b[1m\u001b[38;5;232m\u001b[48;5;154m3\u001b[m\u001b[38;5;231m\u001b[48;5;235m\u001b[38;5;232m\u001b[48;5;154m:\u001b[14;8H"
    ],
    [
      0.043496,
      "\u001b[32;115H40\u001b[m\u001b[38;5;231m\u001b[48;5;235m\u001b[6C\u001b[1m\u001b[38;5;232m\u001b[48;5;154m4\u001b[m\u001b[38;5;231m\u001b[48;5;235m\u001b[38;5;232m\u001b[48;5;154m:\u001b[15;8H"
    ],
    [
      0.043177,
      "\u001b[32;116H2\u001b[m\u001b[38;5;231m\u001b[48;5;235m\u001b[6C\u001b[1m\u001b[38;5;232m\u001b[48;5;154m5\u001b[m\u001b[38;5;231m\u001b[48;5;235m\u001b[38;5;232m\u001b[48;5;154m:\u001b[16;8H"
    ],
    [
      0.048901,
      "\u001b[32;116H5\u001b[m\u001b[38;5;231m\u001b[48;5;235m\u001b[6C\u001b[1m\u001b[38;5;232m\u001b[48;5;154m6\u001b[m\u001b[38;5;231m\u001b[48;5;235m\u001b[38;5;232m\u001b[48;5;154m:\u001b[17;8H"
    ],
    [
      0.041892,
      "\u001b[32;116H8\u001b[m\u001b[38;5;231m\u001b[48;5;235m\u001b[6C\u001b[1m\u001b[38;5;232m\u001b[48;5;154m7\u001b[m\u001b[38;5;231m\u001b[48;5;235m\u001b[38;5;232m\u001b[48;5;154m:  1\u001b[18;5H"
    ],
    [
      0.044702,
      "\u001b[?25l\u001b[m\u001b[38;5;231m\u001b[48;5;235m\u001b[19;5H\u001b[4m\u001b[38;5;197m[\u001b[3C]\u001b[m\u001b[38;5;231m\u001b[48;5;235m\u001b[32;115H\u001b[38;5;232m\u001b[48;5;154m51\u001b[m\u001b[38;5;231m\u001b[48;5;235m\u001b[6C\u001b[1m\u001b[38;5;232m\u001b[48;5;154m8\u001b[m\u001b[38;5;231m\u001b[48;5;235m\u001b[38;5;232m\u001b[48;5;154m:\u001b[19;5H\u001b[?25h"
    ],
    [
      0.045698,
      "\u001b[?25l\u001b[m\u001b[38;5;231m\u001b[48;5;235m\u001b[38;5;197m[rmc]\u001b[m\u001b[38;5;231m\u001b[48;5;235m\u001b[32;116H\u001b[38;5;232m\u001b[48;5;154m4\u001b[m\u001b[38;5;231m\u001b[48;5;235m\u001b[6C\u001b[1m\u001b[38;5;232m\u001b[48;5;154m9\u001b[m\u001b[38;5;231m\u001b[48;5;235m\u001b[38;5;232m\u001b[48;5;154m:  4\u001b[20;8H\u001b[?25h"
    ],
    [
      0.043627,
      "\u001b[32;116H7\u001b[m\u001b[38;5;231m\u001b[48;5;235m\u001b[5C\u001b[1m\u001b[38;5;232m\u001b[48;5;154m20\u001b[m\u001b[38;5;231m\u001b[48;5;235m\u001b[38;5;232m\u001b[48;5;154m:\u001b[21;8H"
    ],
    [
      0.044424,
      "\u001b[32;115H60\u001b[m\u001b[38;5;231m\u001b[48;5;235m\u001b[6C\u001b[1m\u001b[38;5;232m\u001b[48;5;154m1\u001b[m\u001b[38;5;231m\u001b[48;5;235m\u001b[38;5;232m\u001b[48;5;154m:\u001b[22;8H"
    ],
    [
      0.046266,
      "\u001b[32;116H2\u001b[m\u001b[38;5;231m\u001b[48;5;235m\u001b[6C\u001b[1m\u001b[38;5;232m\u001b[48;5;154m2\u001b[m\u001b[38;5;231m\u001b[48;5;235m\u001b[38;5;232m\u001b[48;5;154m:\u001b[23;8H"
    ],
    [
      0.045626,
      "\u001b[32;116H5\u001b[m\u001b[38;5;231m\u001b[48;5;235m\u001b[6C\u001b[1m\u001b[38;5;232m\u001b[48;5;154m3\u001b[m\u001b[38;5;231m\u001b[48;5;235m\u001b[38;5;232m\u001b[48;5;154m:\u001b[24;8H"
    ],
    [
      0.039371,
      "\u001b[32;116H8\u001b[m\u001b[38;5;231m\u001b[48;5;235m\u001b[6C\u001b[1m\u001b[38;5;232m\u001b[48;5;154m4\u001b[m\u001b[38;5;231m\u001b[48;5;235m\u001b[38;5;232m\u001b[48;5;154m:\u001b[25;8H"
    ],
    [
      0.051692,
      "\u001b[32;115H71\u001b[m\u001b[38;5;231m\u001b[48;5;235m\u001b[6C\u001b[1m\u001b[38;5;232m\u001b[48;5;154m5\u001b[m\u001b[38;5;231m\u001b[48;5;235m\u001b[38;5;232m\u001b[48;5;154m:\u001b[26;8H"
    ],
    [
      0.04984,
      "\u001b[?25l\u001b[2;31r\u001b[m\u001b[38;5;231m\u001b[48;5;235m\u001b[31;1H\r\n\u001b[1;33r\u001b[31;1H\u001b[38;5;102m\u001b[48;5;237m 31 \u001b[m\u001b[38;5;231m\u001b[48;5;235m    \u001b[38;5;197mvalid\u001b[m\u001b[38;5;231m\u001b[48;5;235m \u001b[38;5;197musers\u001b[m\u001b[38;5;231m\u001b[48;5;235m = pdbe, rmc\u001b[33;1H\u001b[K\u001b[32;116H\u001b[38;5;232m\u001b[48;5;154m4\u001b[m\u001b[38;5;231m\u001b[48;5;235m\u001b[6C\u001b[1m\u001b[38;5;232m\u001b[48;5;154m6\u001b[m\u001b[38;5;231m\u001b[48;5;235m\u001b[38;5;232m\u001b[48;5;154m:\u001b[26;8H\u001b[?25h"
    ],
    [
      0.041656,
      "\u001b[?25l\u001b[2;31r\u001b[m\u001b[38;5;231m\u001b[48;5;235m\u001b[31;1H\r\n\u001b[1;33r\u001b[31;1H\u001b[38;5;102m\u001b[48;5;237m 32 \u001b[m\u001b[38;5;231m\u001b[48;5;235m    \u001b[38;5;197mread\u001b[m\u001b[38;5;231m\u001b[48;5;235m \u001b[38;5;197monly\u001b[m\u001b[38;5;231m\u001b[48;5;235m = No\u001b[32;116H\u001b[38;5;232m\u001b[48;5;154m7\u001b[m\u001b[38;5;231m\u001b[48;5;235m\u001b[6C\u001b[1m\u001b[38;5;232m\u001b[48;5;154m7\u001b[m\u001b[38;5;231m\u001b[48;5;235m\u001b[38;5;232m\u001b[48;5;154m:  1\u001b[26;5H\u001b[?25h"
    ],
    [
      0.04997,
      "\u001b[?25l\u001b[2;31r\u001b[m\u001b[38;5;231m\u001b[48;5;235m\u001b[31;1H\r\n\u001b[1;33r\u001b[26;5H\u001b[4m\u001b[38;5;197m[\u001b[4C]\u001b[m\u001b[38;5;231m\u001b[48;5;235m\u001b[31;1H\u001b[38;5;102m\u001b[48;5;237m 33 \u001b[m\u001b[38;5;231m\u001b[48;5;235m    \u001b[38;5;197minherit\u001b[m\u001b[38;5;231m\u001b[48;5;235m \u001b[38;5;197mpermissions\u001b[m\u001b[38;5;231m\u001b[48;5;235m = Yes\u001b[32;115H\u001b[38;5;232m\u001b[48;5;154m80\u001b[m\u001b[38;5;231m\u001b[48;5;235m\u001b[6C\u001b[1m\u001b[38;5;232m\u001b[48;5;154m8\u001b[m\u001b[38;5;231m\u001b[48;5;235m\u001b[38;5;232m\u001b[48;5;154m:\u001b[26;5H\u001b[?25h"
    ],
    [
      0.043406,
      "\u001b[?25l\u001b[2;31r\u001b[m\u001b[38;5;231m\u001b[48;5;235m\u001b[31;1H\r\n\u001b[1;33r\u001b[25;5H\u001b[38;5;197m[pdbe]\u001b[m\u001b[38;5;231m\u001b[48;5;235m\u001b[31;1H\u001b[38;5;102m\u001b[48;5;237m 34 \u001b[m\u001b[38;5;231m\u001b[48;5;235m    \u001b[38;5;197minherit\u001b[m\u001b[38;5;231m\u001b[48;5;235m \u001b[38;5;197macls\u001b[m\u001b[38;5;231m\u001b[48;5;235m = Yes\u001b[32;116H\u001b[38;5;232m\u001b[48;5;154m2\u001b[m\u001b[38;5;231m\u001b[48;5;235m\u001b[6C\u001b[1m\u001b[38;5;232m\u001b[48;5;154m9\u001b[m\u001b[38;5;231m\u001b[48;5;235m\u001b[38;5;232m\u001b[48;5;154m:  4\u001b[26;8H\u001b[?25h"
    ],
    [
      0.046467,
      "\u001b[?25l\u001b[2;31r\u001b[m\u001b[38;5;231m\u001b[48;5;235m\u001b[31;1H\r\n\u001b[1;33r\u001b[31;1H\u001b[38;5;102m\u001b[48;5;237m 35 \u001b[m\u001b[38;5;231m\u001b[48;5;235m    \u001b[38;5;197minherit\u001b[m\u001b[38;5;231m\u001b[48;5;235m owner = Yes\u001b[32;116H\u001b[38;5;232m\u001b[48;5;154m5\u001b[m\u001b[38;5;231m\u001b[48;5;235m\u001b[5C\u001b[1m\u001b[38;5;232m\u001b[48;5;154m30\u001b[m\u001b[38;5;231m\u001b[48;5;235m\u001b[38;5;232m\u001b[48;5;154m:\u001b[26;8H\u001b[?25h"
    ],
    [
      0.044088,
      "\u001b[32;116H8\u001b[m\u001b[38;5;231m\u001b[48;5;235m\u001b[6C\u001b[1m\u001b[38;5;232m\u001b[48;5;154m1\u001b[m\u001b[38;5;231m\u001b[48;5;235m\u001b[38;5;232m\u001b[48;5;154m:\u001b[27;8H"
    ],
    [
      0.042045,
      "\u001b[32;115H91\u001b[m\u001b[38;5;231m\u001b[48;5;235m\u001b[6C\u001b[1m\u001b[38;5;232m\u001b[48;5;154m2\u001b[m\u001b[38;5;231m\u001b[48;5;235m\u001b[38;5;232m\u001b[48;5;154m:\u001b[28;8H"
    ],
    [
      0.046371,
      "\u001b[32;116H4\u001b[m\u001b[38;5;231m\u001b[48;5;235m\u001b[6C\u001b[1m\u001b[38;5;232m\u001b[48;5;154m3\u001b[m\u001b[38;5;231m\u001b[48;5;235m\u001b[38;5;232m\u001b[48;5;154m:\u001b[29;8H"
    ],
    [
      0.046873,
      "\u001b[32;116H7\u001b[m\u001b[38;5;231m\u001b[48;5;235m\u001b[6C\u001b[1m\u001b[38;5;232m\u001b[48;5;154m4\u001b[m\u001b[38;5;231m\u001b[48;5;235m\u001b[38;5;232m\u001b[48;5;154m:\u001b[30;8H"
    ],
    [
      0.044917,
      "\u001b[32;114H100\u001b[m\u001b[38;5;231m\u001b[48;5;235m\u001b[6C\u001b[1m\u001b[38;5;232m\u001b[48;5;154m5\u001b[m\u001b[38;5;231m\u001b[48;5;235m\u001b[38;5;232m\u001b[48;5;154m:\u001b[31;8H"
    ],
    [
      0.045853,
      "\u0007"
    ],
    [
      0.538265,
      "\u0007"
    ],
    [
      0.993097,
      "\u001b[?25l\r\n\r\n\u001b[m\u001b[38;5;231m\u001b[48;5;235m:\u001b[?2004h\u001b[?25h"
    ],
    [
      0.367728,
      "q\u001b[?25l\u001b[?25h"
    ],
    [
      0.711936,
      "\r"
    ],
    [
      0.028869,
      "\u001b[?25l"
    ],
    [
      0.004543,
      "\u001b[?2004l"
    ],
    [
      0.103477,
      "\u001b[33;1H\u001b[K\u001b[33;1H\u001b[?2004l\u001b[?1l\u001b>\u001b[?25h\u001b[?1049l"
    ],
    [
      0.007617,
      "\u001b]0;hostmorke@voidstation: ~/dev/ansiblefiles/playbooks/samba-server\u0007~/dev/ansiblefiles/playbooks/samba-server~> "
    ],
    [
      0.471116,
      "v"
    ],
    [
      0.167033,
      "i"
    ],
    [
      0.121689,
      "m"
    ],
    [
      0.239056,
      " "
    ],
    [
      0.904216,
      "s"
    ],
    [
      0.256211,
      "e"
    ],
    [
      0.246913,
      "tup.yml "
    ],
    [
      0.464742,
      "\r\n"
    ],
    [
      0.071976,
      "\u001b[?2004h"
    ],
    [
      0.002837,
      "\u001b[?1049h\u001b[?1h\u001b=\u001b[?2004h"
    ],
    [
      0.001343,
      "\u001b[1;33r\u001b[?12h\u001b[?12l\u001b[27m\u001b[23m\u001b[29m\u001b[m\u001b[38;5;231m\u001b[48;5;235m\u001b[H\u001b[2J\u001b[?25l\u001b[33;1H\"setup.yml\""
    ],
    [
      0.000592,
      " 34L, 970C"
    ],
    [
      0.126141,
      "\u001b[2;1H▽\u001b[6n"
    ],
    [
      0.002988,
      "\u001b[2;1H  \u001b[1;1H"
    ],
    [
      0.000277,
      "\u001b[>c"
    ],
    [
      0.000394,
      "\u001b]10;?\u0007\u001b]11;?\u0007"
    ],
    [
      0.052607,
      "\u001b[1;1H\u001b[38;5;232m\u001b[48;5;154m setup.yml \u001b[m\u001b[38;5;231m\u001b[48;5;235m\u001b[38;5;154m\u001b[48;5;235m\u001b[m\u001b[38;5;231m\u001b[48;5;235m\u001b[1;13H\u001b[38;5;121m\u001b[48;5;235m                                                                                                           \u001b[m\u001b[38;5;231m\u001b[48;5;235m\u001b[38;5;235m\u001b[48;5;235m\u001b[m\u001b[38;5;231m\u001b[48;5;235m\u001b[1;121H\u001b[38;5;214m\u001b[48;5;235m\u001b[m\u001b[38;5;231m\u001b[48;5;235m\u001b[1;122H\u001b[38;5;232m\u001b[48;5;214m buffers \u001b[m\u001b[38;5;231m\u001b[48;5;235m\u001b[2;1H\u001b[38;5;102m\u001b[48;5;237m  1 \u001b[m\u001b[38;5;231m\u001b[48;5;235m\u001b[38;5;197m---\u001b[m\u001b[38;5;231m\u001b[48;5;235m\r\n\u001b[38;5;102m\u001b[48;5;237m  2 \u001b[m\u001b[38;5;231m\u001b[48;5;235m\u001b[38;5;186m- \u001b[m\u001b[38;5;231m\u001b[48;5;235m\u001b[38;5;81mhosts\u001b[m\u001b[38;5;231m\u001b[48;5;235m\u001b[38;5;231m:\u001b[m\u001b[38;5;231m\u001b[48;5;235m nas\r\n\u001b[38;5;102m\u001b[48;5;237m  3 \u001b[m\u001b[38;5;231m\u001b[48;5;235m  \u001b[38;5;81mbecome\u001b[m\u001b[38;5;231m\u001b[48;5;235m\u001b[38;5;231m:\u001b[m\u001b[38;5;231m\u001b[48;5;235m yes\r\n\u001b[38;5;102m\u001b[48;5;237m  4 \u001b[m\u001b[38;5;231m\u001b[48;5;235m  \u001b[38;5;81mtasks\u001b[m\u001b[38;5;231m\u001b[48;5;235m\u001b[38;5;231m:\u001b[m\u001b[38;5;231m\u001b[48;5;235m\r\n\u001b[38;5;102m\u001b[48;5;237m  5 \u001b[m\u001b[38;5;23"
    ],
    [
      8.7e-05,
      "1m\u001b[48;5;235m    \u001b[38;5;186m- \u001b[m\u001b[38;5;231m\u001b[48;5;235m\u001b[38;5;81mname\u001b[m\u001b[38;5;231m\u001b[48;5;235m\u001b[38;5;231m:\u001b[m\u001b[38;5;231m\u001b[48;5;235m Create users\r\n\u001b[38;5;102m\u001b[48;5;237m  6 \u001b[m\u001b[38;5;231m\u001b[48;5;235m      \u001b[38;5;81muser\u001b[m\u001b[38;5;231m\u001b[48;5;235m\u001b[38;5;231m:\u001b[m\u001b[38;5;231m\u001b[48;5;235m name={{item}} createhome=no shell=/usr/sbin/nologin\r\n\u001b[38;5;102m\u001b[48;5;237m  7 \u001b[m\u001b[38;5;231m\u001b[48;5;235m      \u001b[38;5;81mwith_items\u001b[m\u001b[38;5;231m\u001b[48;5;235m\u001b[38;5;231m:\u001b[m\u001b[38;5;231m\u001b[48;5;235m\r\n\u001b[38;5;102m\u001b[48;5;237m  8 \u001b[m\u001b[38;5;231m\u001b[48;5;235m\u001b[8C\u001b[38;5;186m- \u001b[m\u001b[38;5;231m\u001b[48;5;235mpdbe\r\n\u001b[38;5;102m\u001b[48;5;237m  9 \u001b[m\u001b[38;5;231m\u001b[48;5;235m\u001b[8C\u001b[38;5;186m- \u001b[m\u001b[38;5;231m\u001b[48;5;235mrmc\r\n\u001b[38;5;102m\u001b[48;5;237m 10 \r\n 11 \u001b[m\u001b[38;5;231m\u001b[48;5;235m    \u001b[38;5;186m- \u001b[m\u001b[38;5;231m\u001b[48;5;235m\u001b[38;5;81mname\u001b[m\u001b[38;5;231m\u001b[48;5;235m\u001b[38;5;231m:\u001b[m\u001b[38;5;231m\u001b[48;5;235m Create user dirs\r\n\u001b[38;5;102m\u001b[48;5;237m 12 \u001b[m\u001b[38;5;231m\u001b[48;5;235m      \u001b[38;5;81mfile\u001b[m\u001b[38;5;231m\u001b[48;5;235m\u001b[38;5;231m:\u001b[m\u001b[38;5;231m\u001b[48;5;235m name={{item.path}} owner"
    ],
    [
      0.035578,
      "={{item.user}} mode=0777 recurse=yes state=directory\r\n\u001b[38;5;102m\u001b[48;5;237m 13 \u001b[m\u001b[38;5;231m\u001b[48;5;235m      \u001b[38;5;81mwith_items\u001b[m\u001b[38;5;231m\u001b[48;5;235m\u001b[38;5;231m:\u001b[m\u001b[38;5;231m\u001b[48;5;235m\r\n\u001b[38;5;102m\u001b[48;5;237m 14 \u001b[m\u001b[38;5;231m\u001b[48;5;235m\u001b[8C\u001b[38;5;186m- \u001b[m\u001b[38;5;231m\u001b[48;5;235m\u001b[38;5;231m{\u001b[m\u001b[38;5;231m\u001b[48;5;235m\u001b[38;5;81mpath\u001b[m\u001b[38;5;231m\u001b[48;5;235m\u001b[38;5;231m:\u001b[m\u001b[38;5;231m\u001b[48;5;235m \u001b[38;5;186m'/mnt/storage/pdbe'\u001b[m\u001b[38;5;231m\u001b[48;5;235m, \u001b[38;5;81muser\u001b[m\u001b[38;5;231m\u001b[48;5;235m\u001b[38;5;231m:\u001b[m\u001b[38;5;231m\u001b[48;5;235m \u001b[38;5;186m'pdbe'\u001b[m\u001b[38;5;231m\u001b[48;5;235m\u001b[38;5;231m}\u001b[m\u001b[38;5;231m\u001b[48;5;235m\r\n\u001b[38;5;102m\u001b[48;5;237m 15 \u001b[m\u001b[38;5;231m\u001b[48;5;235m\u001b[8C\u001b[38;5;186m- \u001b[m\u001b[38;5;231m\u001b[48;5;235m\u001b[38;5;231m{\u001b[m\u001b[38;5;231m\u001b[48;5;235m\u001b[38;5;81mpath\u001b[m\u001b[38;5;231m\u001b[48;5;235m\u001b[38;5;231m:\u001b[m\u001b[38;5;231m\u001b[48;5;235m \u001b[38;5;186m'/mnt/storage/rmc'\u001b[m\u001b[38;5;231m\u001b[48;5;235m, \u001b[38;5;81muser\u001b[m\u001b[38;5;231m\u001b[48;5;235m\u001b[38;5;231m:\u001b[m\u001b[38;5;231m\u001b[48;5;235m \u001b[38;5;186m'rmc'\u001b[m\u001b[38;5;231m\u001b[48;5;235m\u001b[38;5;231m}\u001b[m\u001b[38;5;231m"
    ],
    [
      8.3e-05,
      "\u001b[48;5;235m\r\n\u001b[38;5;102m\u001b[48;5;237m 16 \r\n 17 \u001b[m\u001b[38;5;231m\u001b[48;5;235m    \u001b[38;5;186m- \u001b[m\u001b[38;5;231m\u001b[48;5;235m\u001b[38;5;81mname\u001b[m\u001b[38;5;231m\u001b[48;5;235m\u001b[38;5;231m:\u001b[m\u001b[38;5;231m\u001b[48;5;235m Install SAMBA\r\n\u001b[38;5;102m\u001b[48;5;237m 18 \u001b[m\u001b[38;5;231m\u001b[48;5;235m      \u001b[38;5;81mapt\u001b[m\u001b[38;5;231m\u001b[48;5;235m\u001b[38;5;231m:\u001b[m\u001b[38;5;231m\u001b[48;5;235m name=samba update_cache=yes state=installed\r\n\u001b[38;5;102m\u001b[48;5;237m 19 \r\n 20 \u001b[m\u001b[38;5;231m\u001b[48;5;235m    \u001b[38;5;186m- \u001b[m\u001b[38;5;231m\u001b[48;5;235m\u001b[38;5;81mname\u001b[m\u001b[38;5;231m\u001b[48;5;235m\u001b[38;5;231m:\u001b[m\u001b[38;5;231m\u001b[48;5;235m Add users to SAMBA\r\n\u001b[38;5;102m\u001b[48;5;237m 21 \u001b[m\u001b[38;5;231m\u001b[48;5;235m      \u001b[38;5;81mshell\u001b[m\u001b[38;5;231m\u001b[48;5;235m\u001b[38;5;231m:\u001b[m\u001b[38;5;231m\u001b[48;5;235m \u001b[38;5;186m'(echo {{ item.pass }}; echo {{ item.pass }}) | smbpasswd -s -a {{ item.user }}'\u001b[m\u001b[38;5;231m\u001b[48;5;235m\r\n\u001b[38;5;102m\u001b[48;5;237m 22 \u001b[m\u001b[38;5;231m\u001b[48;5;235m      \u001b[38;5;81mwith_items\u001b[m\u001b[38;5;231m\u001b[48;5;235m\u001b[38;5;231m:\u001b[m\u001b[38;5;231m\u001b[48;5;235m\r\n\u001b[38;5;102m\u001b[48;5;237m 23 \u001b[m\u001b[38;5;231m"
    ],
    [
      0.024877,
      "\u001b[48;5;235m\u001b[8C\u001b[38;5;186m- \u001b[m\u001b[38;5;231m\u001b[48;5;235m\u001b[38;5;231m{\u001b[m\u001b[38;5;231m\u001b[48;5;235m\u001b[38;5;81muser\u001b[m\u001b[38;5;231m\u001b[48;5;235m\u001b[38;5;231m:\u001b[m\u001b[38;5;231m\u001b[48;5;235m \u001b[38;5;186m'pdbe'\u001b[m\u001b[38;5;231m\u001b[48;5;235m, \u001b[38;5;81mpass\u001b[m\u001b[38;5;231m\u001b[48;5;235m\u001b[38;5;231m:\u001b[m\u001b[38;5;231m\u001b[48;5;235m \u001b[38;5;186m'1'\u001b[m\u001b[38;5;231m\u001b[48;5;235m\u001b[38;5;231m}\u001b[m\u001b[38;5;231m\u001b[48;5;235m\r\n\u001b[38;5;102m\u001b[48;5;237m 24 \u001b[m\u001b[38;5;231m\u001b[48;5;235m\u001b[8C\u001b[38;5;186m- \u001b[m\u001b[38;5;231m\u001b[48;5;235m\u001b[38;5;231m{\u001b[m\u001b[38;5;231m\u001b[48;5;235m\u001b[38;5;81muser\u001b[m\u001b[38;5;231m\u001b[48;5;235m\u001b[38;5;231m:\u001b[m\u001b[38;5;231m\u001b[48;5;235m \u001b[38;5;186m'rmc'\u001b[m\u001b[38;5;231m\u001b[48;5;235m, \u001b[38;5;81mpass\u001b[m\u001b[38;5;231m\u001b[48;5;235m\u001b[38;5;231m:\u001b[m\u001b[38;5;231m\u001b[48;5;235m \u001b[38;5;186m'2014'\u001b[m\u001b[38;5;231m\u001b[48;5;235m\u001b[38;5;231m}\u001b[m\u001b[38;5;231m\u001b[48;5;235m\r\n\u001b[38;5;102m\u001b[48;5;237m 25 \r\n 26 \u001b[m\u001b[38;5;231m\u001b[48;5;235m    \u001b[38;5;186m- \u001b[m\u001b[38;5;231m\u001b[48;5;235m\u001b[38;5;81mname\u001b[m\u001b[38;5;231m\u001b[48;5;235m\u001b[38;5;231m:\u001b[m\u001b[38;5;231m\u001b[48;5;235m Copy config\r\n\u001b[38;5;102m\u001b[48;5;237m 27 \u001b[m\u001b[38;5;231m\u001b[48;5;235m      \u001b[38"
    ],
    [
      0.000109,
      ";5;81mcopy\u001b[m\u001b[38;5;231m\u001b[48;5;235m\u001b[38;5;231m:\u001b[m\u001b[38;5;231m\u001b[48;5;235m src=files/smb.conf dest=/etc/samba/smb.conf\r\n\u001b[38;5;102m\u001b[48;5;237m 28 \r\n 29 \u001b[m\u001b[38;5;231m\u001b[48;5;235m    \u001b[38;5;186m- \u001b[m\u001b[38;5;231m\u001b[48;5;235m\u001b[38;5;81mname\u001b[m\u001b[38;5;231m\u001b[48;5;235m\u001b[38;5;231m:\u001b[m\u001b[38;5;231m\u001b[48;5;235m Restart  SMB service\r\n\u001b[38;5;102m\u001b[48;5;237m 30 \u001b[m\u001b[38;5;231m\u001b[48;5;235m      \u001b[38;5;81msystemd\u001b[m\u001b[38;5;231m\u001b[48;5;235m\u001b[38;5;231m:\u001b[m\u001b[38;5;231m\u001b[48;5;235m name=smbd state=restarted enabled=yes\r\n\u001b[38;5;232m\u001b[48;5;154m \u001b[m\u001b[38;5;231m\u001b[48;5;235m\u001b[1m\u001b[38;5;232m\u001b[48;5;154mNORMAL\u001b[m\u001b[38;5;231m\u001b[48;5;235m\u001b[38;5;232m\u001b[48;5;154m \u001b[m\u001b[38;5;231m\u001b[48;5;235m\u001b[38;5;154m\u001b[48;5;238m\u001b[m\u001b[38;5;231m\u001b[48;5;235m\u001b[32;10H\u001b[38;5;238m\u001b[48;5;235m\u001b[m\u001b[38;5;231m\u001b[48;5;235m\u001b[32;11H\u001b[38;5;121m\u001b[48;5;235m setup.yml                                                                      \u001b[m\u001b[38;5;231m\u001b[48;5;235m\u001b[38;5;235m\u001b[48;5;235m\u001b[m\u001b[38;5;231m\u001b[48;5;235m\u001b[32;92H\u001b[38;5;121m\u001b[48;5;235m yaml \u001b[m\u001b[38;5;231m\u001b[48;5;235m\u001b[38;5;238m"
    ],
    [
      0.005306,
      "\u001b[48;5;235m\u001b[m\u001b[38;5;231m\u001b[48;5;235m\u001b[32;99H\u001b[38;5;222m\u001b[48;5;238m utf-8[unix] \u001b[m\u001b[38;5;231m\u001b[48;5;235m\u001b[38;5;154m\u001b[48;5;238m\u001b[m\u001b[38;5;231m\u001b[48;5;235m\u001b[32;113H\u001b[38;5;232m\u001b[48;5;154m   2% \u001b[m\u001b[38;5;231m\u001b[48;5;235m\u001b[32;120H\u001b[1m\u001b[38;5;232m\u001b[48;5;154m   1\u001b[m\u001b[38;5;231m\u001b[48;5;235m\u001b[38;5;232m\u001b[48;5;154m:  1  \u001b[m\u001b[38;5;231m\u001b[48;5;235m\u001b[38;5;166m\u001b[48;5;154m\u001b[2;5H\u001b[?25h"
    ],
    [
      0.854122,
      "\u001b[m\u001b[38;5;231m\u001b[48;5;235m\u001b[32;116H\u001b[38;5;232m\u001b[48;5;154m5\u001b[m\u001b[38;5;231m\u001b[48;5;235m\u001b[6C\u001b[1m\u001b[38;5;232m\u001b[48;5;154m2\u001b[m\u001b[38;5;231m\u001b[48;5;235m\u001b[38;5;232m\u001b[48;5;154m:\u001b[3;5H"
    ],
    [
      0.674769,
      "\u001b[32;116H8\u001b[m\u001b[38;5;231m\u001b[48;5;235m\u001b[6C\u001b[1m\u001b[38;5;232m\u001b[48;5;154m3\u001b[m\u001b[38;5;231m\u001b[48;5;235m\u001b[38;5;232m\u001b[48;5;154m:\u001b[4;5H"
    ],
    [
      0.039967,
      "\u001b[32;115H11\u001b[m\u001b[38;5;231m\u001b[48;5;235m\u001b[6C\u001b[1m\u001b[38;5;232m\u001b[48;5;154m4\u001b[m\u001b[38;5;231m\u001b[48;5;235m\u001b[38;5;232m\u001b[48;5;154m:\u001b[5;5H"
    ],
    [
      0.043047,
      "\u001b[32;116H4\u001b[m\u001b[38;5;231m\u001b[48;5;235m\u001b[6C\u001b[1m\u001b[38;5;232m\u001b[48;5;154m5\u001b[m\u001b[38;5;231m\u001b[48;5;235m\u001b[38;5;232m\u001b[48;5;154m:\u001b[6;5H"
    ],
    [
      0.040275,
      "\u001b[32;116H7\u001b[m\u001b[38;5;231m\u001b[48;5;235m\u001b[6C\u001b[1m\u001b[38;5;232m\u001b[48;5;154m6\u001b[m\u001b[38;5;231m\u001b[48;5;235m\u001b[38;5;232m\u001b[48;5;154m:\u001b[7;5H"
    ],
    [
      0.051281,
      "\u001b[32;115H20\u001b[m\u001b[38;5;231m\u001b[48;5;235m\u001b[6C\u001b[1m\u001b[38;5;232m\u001b[48;5;154m7\u001b[m\u001b[38;5;231m\u001b[48;5;235m\u001b[38;5;232m\u001b[48;5;154m:\u001b[8;5H"
    ],
    [
      0.04569,
      "\u001b[32;116H3\u001b[m\u001b[38;5;231m\u001b[48;5;235m\u001b[6C\u001b[1m\u001b[38;5;232m\u001b[48;5;154m8\u001b[m\u001b[38;5;231m\u001b[48;5;235m\u001b[38;5;232m\u001b[48;5;154m:\u001b[9;5H"
    ],
    [
      0.045633,
      "\u001b[32;116H6\u001b[m\u001b[38;5;231m\u001b[48;5;235m\u001b[6C\u001b[1m\u001b[38;5;232m\u001b[48;5;154m9\u001b[m\u001b[38;5;231m\u001b[48;5;235m\u001b[38;5;232m\u001b[48;5;154m:\u001b[10;5H"
    ],
    [
      0.045574,
      "\u001b[32;116H9\u001b[m\u001b[38;5;231m\u001b[48;5;235m\u001b[5C\u001b[1m\u001b[38;5;232m\u001b[48;5;154m10\u001b[m\u001b[38;5;231m\u001b[48;5;235m\u001b[38;5;232m\u001b[48;5;154m:\u001b[11;5H"
    ],
    [
      0.045427,
      "\u001b[32;115H32\u001b[m\u001b[38;5;231m\u001b[48;5;235m\u001b[6C\u001b[1m\u001b[38;5;232m\u001b[48;5;154m1\u001b[m\u001b[38;5;231m\u001b[48;5;235m\u001b[38;5;232m\u001b[48;5;154m:\u001b[12;5H"
    ],
    [
      0.042697,
      "\u001b[32;116H5\u001b[m\u001b[38;5;231m\u001b[48;5;235m\u001b[6C\u001b[1m\u001b[38;5;232m\u001b[48;5;154m2\u001b[m\u001b[38;5;231m\u001b[48;5;235m\u001b[38;5;232m\u001b[48;5;154m:\u001b[13;5H"
    ],
    [
      0.044793,
      "\u001b[32;116H8\u001b[m\u001b[38;5;231m\u001b[48;5;235m\u001b[6C\u001b[1m\u001b[38;5;232m\u001b[48;5;154m3\u001b[m\u001b[38;5;231m\u001b[48;5;235m\u001b[38;5;232m\u001b[48;5;154m:\u001b[14;5H"
    ],
    [
      0.046862,
      "\u001b[32;115H41\u001b[m\u001b[38;5;231m\u001b[48;5;235m\u001b[6C\u001b[1m\u001b[38;5;232m\u001b[48;5;154m4\u001b[m\u001b[38;5;231m\u001b[48;5;235m\u001b[38;5;232m\u001b[48;5;154m:\u001b[15;5H"
    ],
    [
      0.041121,
      "\u001b[32;116H4\u001b[m\u001b[38;5;231m\u001b[48;5;235m\u001b[6C\u001b[1m\u001b[38;5;232m\u001b[48;5;154m5\u001b[m\u001b[38;5;231m\u001b[48;5;235m\u001b[38;5;232m\u001b[48;5;154m:\u001b[16;5H"
    ],
    [
      0.045546,
      "\u001b[32;116H7\u001b[m\u001b[38;5;231m\u001b[48;5;235m\u001b[6C\u001b[1m\u001b[38;5;232m\u001b[48;5;154m6\u001b[m\u001b[38;5;231m\u001b[48;5;235m\u001b[38;5;232m\u001b[48;5;154m:\u001b[17;5H"
    ],
    [
      0.044621,
      "\u001b[32;115H50\u001b[m\u001b[38;5;231m\u001b[48;5;235m\u001b[6C\u001b[1m\u001b[38;5;232m\u001b[48;5;154m7\u001b[m\u001b[38;5;231m\u001b[48;5;235m\u001b[38;5;232m\u001b[48;5;154m:\u001b[18;5H"
    ],
    [
      0.044378,
      "\u001b[32;116H2\u001b[m\u001b[38;5;231m\u001b[48;5;235m\u001b[6C\u001b[1m\u001b[38;5;232m\u001b[48;5;154m8\u001b[m\u001b[38;5;231m\u001b[48;5;235m\u001b[38;5;232m\u001b[48;5;154m:\u001b[19;5H"
    ],
    [
      0.045326,
      "\u001b[32;116H5\u001b[m\u001b[38;5;231m\u001b[48;5;235m\u001b[6C\u001b[1m\u001b[38;5;232m\u001b[48;5;154m9\u001b[m\u001b[38;5;231m\u001b[48;5;235m\u001b[38;5;232m\u001b[48;5;154m:\u001b[20;5H"
    ],
    [
      0.043948,
      "\u001b[32;116H8\u001b[m\u001b[38;5;231m\u001b[48;5;235m\u001b[5C\u001b[1m\u001b[38;5;232m\u001b[48;5;154m20\u001b[m\u001b[38;5;231m\u001b[48;5;235m\u001b[38;5;232m\u001b[48;5;154m:\u001b[21;5H"
    ],
    [
      0.044303,
      "\u001b[32;115H61\u001b[m\u001b[38;5;231m\u001b[48;5;235m\u001b[6C\u001b[1m\u001b[38;5;232m\u001b[48;5;154m1\u001b[m\u001b[38;5;231m\u001b[48;5;235m\u001b[38;5;232m\u001b[48;5;154m:\u001b[22;5H"
    ],
    [
      0.053072,
      "\u001b[32;116H4\u001b[m\u001b[38;5;231m\u001b[48;5;235m\u001b[6C\u001b[1m\u001b[38;5;232m\u001b[48;5;154m2\u001b[m\u001b[38;5;231m\u001b[48;5;235m\u001b[38;5;232m\u001b[48;5;154m:\u001b[23;5H"
    ],
    [
      0.03953,
      "\u001b[32;116H7\u001b[m\u001b[38;5;231m\u001b[48;5;235m\u001b[6C\u001b[1m\u001b[38;5;232m\u001b[48;5;154m3\u001b[m\u001b[38;5;231m\u001b[48;5;235m\u001b[38;5;232m\u001b[48;5;154m:\u001b[24;5H"
    ],
    [
      0.042926,
      "\u001b[32;115H70\u001b[m\u001b[38;5;231m\u001b[48;5;235m\u001b[6C\u001b[1m\u001b[38;5;232m\u001b[48;5;154m4\u001b[m\u001b[38;5;231m\u001b[48;5;235m\u001b[38;5;232m\u001b[48;5;154m:\u001b[25;5H"
    ],
    [
      0.046303,
      "\u001b[32;116H3\u001b[m\u001b[38;5;231m\u001b[48;5;235m\u001b[6C\u001b[1m\u001b[38;5;232m\u001b[48;5;154m5\u001b[m\u001b[38;5;231m\u001b[48;5;235m\u001b[38;5;232m\u001b[48;5;154m:\u001b[26;5H"
    ],
    [
      0.045505,
      "\u001b[?25l\u001b[2;31r\u001b[m\u001b[38;5;231m\u001b[48;5;235m\u001b[31;1H\r\n\u001b[1;33r\u001b[31;1H\u001b[38;5;102m\u001b[48;5;237m 31 \u001b[m\u001b[38;5;231m\u001b[48;5;235m\u001b[33;1H\u001b[K\u001b[32;116H\u001b[38;5;232m\u001b[48;5;154m6\u001b[m\u001b[38;5;231m\u001b[48;5;235m\u001b[6C\u001b[1m\u001b[38;5;232m\u001b[48;5;154m6\u001b[m\u001b[38;5;231m\u001b[48;5;235m\u001b[38;5;232m\u001b[48;5;154m:\u001b[26;5H\u001b[?25h"
    ],
    [
      0.045378,
      "\u001b[?25l\u001b[2;31r\u001b[m\u001b[38;5;231m\u001b[48;5;235m\u001b[31;1H\r\n\u001b[1;33r\u001b[31;1H\u001b[38;5;102m\u001b[48;5;237m 32 \u001b[m\u001b[38;5;231m\u001b[48;5;235m    \u001b[38;5;186m- \u001b[m\u001b[38;5;231m\u001b[48;5;235m\u001b[38;5;81mname\u001b[m\u001b[38;5;231m\u001b[48;5;235m\u001b[38;5;231m:\u001b[m\u001b[38;5;231m\u001b[48;5;235m Restart NMB service\u001b[32;116H\u001b[38;5;232m\u001b[48;5;154m9\u001b[m\u001b[38;5;231m\u001b[48;5;235m\u001b[6C\u001b[1m\u001b[38;5;232m\u001b[48;5;154m7\u001b[m\u001b[38;5;231m\u001b[48;5;235m\u001b[38;5;232m\u001b[48;5;154m:\u001b[26;5H\u001b[?25h"
    ],
    [
      0.057985,
      "\u001b[?25l\u001b[2;31r\u001b[m\u001b[38;5;231m\u001b[48;5;235m\u001b[31;1H\r\n\u001b[1;33r\u001b[31;1H\u001b[38;5;102m\u001b[48;5;237m 33 \u001b[m\u001b[38;5;231m\u001b[48;5;235m      \u001b[38;5;81msystemd\u001b[m\u001b[38;5;231m\u001b[48;5;235m\u001b[38;5;231m:\u001b[m\u001b[38;5;231m\u001b[48;5;235m name=nmbd state=restarted enabled=yes\u001b[32;115H\u001b[38;5;232m\u001b[48;5;154m82\u001b[m\u001b[38;5;231m\u001b[48;5;235m\u001b[6C\u001b[1m\u001b[38;5;232m\u001b[48;5;154m8\u001b[m\u001b[38;5;231m\u001b[48;5;235m\u001b[38;5;232m\u001b[48;5;154m:\u001b[26;5H\u001b[?25h"
    ],
    [
      0.044977,
      "\u001b[?25l\u001b[2;31r\u001b[m\u001b[38;5;231m\u001b[48;5;235m\u001b[31;1H\r\n\u001b[1;33r\u001b[31;1H\u001b[38;5;102m\u001b[48;5;237m 34 \u001b[m\u001b[38;5;231m\u001b[48;5;235m\u001b[32;116H\u001b[38;5;232m\u001b[48;5;154m5\u001b[m\u001b[38;5;231m\u001b[48;5;235m\u001b[6C\u001b[1m\u001b[38;5;232m\u001b[48;5;154m9\u001b[m\u001b[38;5;231m\u001b[48;5;235m\u001b[38;5;232m\u001b[48;5;154m:\u001b[26;5H\u001b[?25h"
    ],
    [
      0.036738,
      "\u001b[32;116H8\u001b[m\u001b[38;5;231m\u001b[48;5;235m\u001b[5C\u001b[1m\u001b[38;5;232m\u001b[48;5;154m30\u001b[m\u001b[38;5;231m\u001b[48;5;235m\u001b[38;5;232m\u001b[48;5;154m:\u001b[27;5H"
    ],
    [
      0.040096,
      "\u001b[32;115H91\u001b[m\u001b[38;5;231m\u001b[48;5;235m\u001b[6C\u001b[1m\u001b[38;5;232m\u001b[48;5;154m1\u001b[m\u001b[38;5;231m\u001b[48;5;235m\u001b[38;5;232m\u001b[48;5;154m:\u001b[28;5H"
    ],
    [
      0.046774,
      "\u001b[32;116H4\u001b[m\u001b[38;5;231m\u001b[48;5;235m\u001b[6C\u001b[1m\u001b[38;5;232m\u001b[48;5;154m2\u001b[m\u001b[38;5;231m\u001b[48;5;235m\u001b[38;5;232m\u001b[48;5;154m:\u001b[29;5H"
    ],
    [
      0.044957,
      "\u001b[32;116H7\u001b[m\u001b[38;5;231m\u001b[48;5;235m\u001b[6C\u001b[1m\u001b[38;5;232m\u001b[48;5;154m3\u001b[m\u001b[38;5;231m\u001b[48;5;235m\u001b[38;5;232m\u001b[48;5;154m:\u001b[30;5H"
    ],
    [
      0.043934,
      "\u001b[32;114H100\u001b[m\u001b[38;5;231m\u001b[48;5;235m\u001b[6C\u001b[1m\u001b[38;5;232m\u001b[48;5;154m4\u001b[m\u001b[38;5;231m\u001b[48;5;235m\u001b[38;5;232m\u001b[48;5;154m:\u001b[31;5H"
    ],
    [
      0.042494,
      "\u0007"
    ],
    [
      1.834734,
      "\u001b[?25l\r\n\r\n\u001b[m\u001b[38;5;231m\u001b[48;5;235m:\u001b[?2004h\u001b[?25h"
    ],
    [
      0.424155,
      "q\u001b[?25l\u001b[?25h"
    ],
    [
      1.105744,
      "\r"
    ],
    [
      0.02746,
      "\u001b[?25l"
    ],
    [
      0.003341,
      "\u001b[?2004l"
    ],
    [
      0.10405,
      "\u001b[33;1H\u001b[K\u001b[33;1H\u001b[?2004l\u001b[?1l\u001b>\u001b[?25h\u001b[?1049l"
    ],
    [
      0.00645,
      "\u001b]0;hostmorke@voidstation: ~/dev/ansiblefiles/playbooks/samba-server\u0007~/dev/ansiblefiles/playbooks/samba-server~> "
    ],
    [
      0.520981,
      "a"
    ],
    [
      0.151974,
      "n"
    ],
    [
      0.183811,
      "s"
    ],
    [
      0.271997,
      "i"
    ],
    [
      0.26558,
      "\u0007"
    ],
    [
      0.002952,
      "ble"
    ],
    [
      0.907895,
      "-"
    ],
    [
      0.29566,
      "p"
    ],
    [
      0.06385,
      "l"
    ],
    [
      0.197232,
      "aybook "
    ],
    [
      2.0,
      "s"
    ],
    [
      0.263905,
      "e"
    ],
    [
      0.14359,
      "t"
    ],
    [
      0.223341,
      "up.yml "
    ],
    [
      1.080884,
      "-"
    ],
    [
      0.416122,
      "K"
    ],
    [
      0.808953,
      "\r\n"
    ],
    [
      2.0,
      "SUDO password: "
    ],
    [
      2.0,
      "\r\n"
    ],
    [
      1.523263,
      "\r\nPLAY [nas] ***********************************************************************************************************************\r\n"
    ],
    [
      0.068918,
      "\r\nTASK [Gathering Facts] ***********************************************************************************************************\r\n"
    ],
    [
      2.0,
      "\u001b[0;32mok: [10.69.0.199]\u001b[0m\r\n"
    ],
    [
      0.045451,
      "\r\nTASK [Create users] **************************************************************************************************************\r\n"
    ],
    [
      2.0,
      "\u001b[0;33mchanged: [10.69.0.199] => (item=pdbe)\u001b[0m\r\n"
    ],
    [
      1.160219,
      "\u001b[0;33mchanged: [10.69.0.199] => (item=rmc)\u001b[0m\r\n"
    ],
    [
      0.066522,
      "\r\nTASK [Create user dirs] **********************************************************************************************************\r\n"
    ],
    [
      1.795473,
      "\u001b[0;33mchanged: [10.69.0.199] => (item={'path': '/mnt/storage/pdbe', 'user': 'pdbe'})\u001b[0m\r\n"
    ],
    [
      0.93869,
      "\u001b[0;33mchanged: [10.69.0.199] => (item={'path': '/mnt/storage/rmc', 'user': 'rmc'})\u001b[0m\r\n"
    ],
    [
      0.064879,
      "\r\nTASK [Install SAMBA] *************************************************************************************************************\r\n"
    ],
    [
      2.0,
      "\u001b[0;33mchanged: [10.69.0.199]\u001b[0m"
    ],
    [
      0.002984,
      "\r\n"
    ],
    [
      0.057634,
      "\r\nTASK [Add users to SAMBA] ********************************************************************************************************\r\n"
    ],
    [
      1.902159,
      "\u001b[0;33mchanged: [10.69.0.199] => (item={'user': 'pdbe', 'pass': '1'})\u001b[0m\r\n"
    ],
    [
      1.250523,
      "\u001b[0;33mchanged: [10.69.0.199] => (item={'user': 'rmc', 'pass': '2014'})\u001b[0m\r\n"
    ],
    [
      0.071004,
      "\r\nTASK [Copy config] ***************************************************************************************************************\r\n"
    ],
    [
      2.0,
      "\u001b[0;33mchanged: [10.69.0.199]\u001b[0m\r\n"
    ],
    [
      0.064843,
      "\r\nTASK [Restart  SMB service] ******************************************************************************************************\r\n"
    ],
    [
      2.0,
      "\u001b[0;33mchanged: [10.69.0.199]\u001b[0m\r\n"
    ],
    [
      0.059012,
      "\r\nTASK [Restart NMB service] *******************************************************************************************************\r\n"
    ],
    [
      1.194707,
      "\u001b[0;33mchanged: [10.69.0.199]\u001b[0m\r\n"
    ],
    [
      0.021106,
      "\r\nPLAY RECAP ***********************************************************************************************************************\r\n"
    ],
    [
      0.000675,
      "\u001b[0;33m10.69.0.199\u001b[0m                : \u001b[0;32mok=8   \u001b[0m \u001b[0;33mchanged=7   \u001b[0m unreachable=0    failed=0   \r\n"
    ],
    [
      0.000496,
      "\r\n"
    ],
    [
      0.278298,
      "\u001b]0;hostmorke@voidstation: ~/dev/ansiblefiles/playbooks/samba-server\u0007~/dev/ansiblefiles/playbooks/samba-server~> "
    ]
  ]
}